fujitsu_quantum/__init__.py
fujitsu_quantum/auth.py
fujitsu_quantum/aws_utils.py
fujitsu_quantum/config.py
fujitsu_quantum/devices.py
fujitsu_quantum/logging.py
fujitsu_quantum/requests.py
fujitsu_quantum/results.py
fujitsu_quantum/session.py
fujitsu_quantum/storage.py
fujitsu_quantum/tasks.py
fujitsu_quantum/types.py
fujitsu_quantum/utils.py
fujitsu_quantum/warnings.py
fujitsu_quantum/api/__init__.py
fujitsu_quantum/api/api.py
fujitsu_quantum/api/grpc_client.py
fujitsu_quantum/api/user_pb2.py
fujitsu_quantum/api/user_pb2.pyi
fujitsu_quantum/api/user_pb2_grpc.py
fujitsu_quantum/cmd/__init__.py
fujitsu_quantum/cmd/cli.py
fujitsu_quantum/plugins/__init__.py
fujitsu_quantum/plugins/openfermion/__init__.py
fujitsu_quantum/plugins/openfermion/operators.py
fujitsu_quantum/plugins/qiskit/__init__.py
fujitsu_quantum/plugins/qiskit/operators.py
fujitsu_quantum/plugins/qiskit/qasm.py
fujitsu_quantum/plugins/qulacs/__init__.py
fujitsu_quantum/plugins/qulacs/operators.py
fujitsu_quantum/plugins/qulacs/qasm.py
fujitsu_quantum-2.2.0.dist-info/METADATA
fujitsu_quantum-2.2.0.dist-info/WHEEL
fujitsu_quantum-2.2.0.dist-info/entry_points.txt
fujitsu_quantum-2.2.0.dist-info/RECORD
