Metadata-Version: 2.4
Name: fujitsu-quantum
Version: 2.2.0
Summary: Fujitsu Quantum Cloud SDK
Author: Fujitsu Limited
Requires-Python: >=3.10
Requires-Dist: boto3~=1.36
Requires-Dist: cryptography~=44.0
Requires-Dist: filelock~=3.17
Requires-Dist: grpcio~=1.70
Requires-Dist: protobuf~=5.29
Requires-Dist: pycognito~=2024.5
Requires-Dist: pyjson5~=1.6
Requires-Dist: requests~=2.32
